{
  "project_info": {
    "project_number": "978324396478",
    "firebase_url": "https://yo-android-staging.firebaseio.com",
    "project_id": "yo-android-staging",
    "storage_bucket": "yo-android-staging.appspot.com"
  },
  "client": [
    {
      "client_info": {
        "mobilesdk_app_id": "1:978324396478:android:eea401b15cfd8ccb",
        "android_client_info": {
          "package_name": "com.yo.android.stage"
        }
      },
      "oauth_client": [
        {
          "client_id": "978324396478-hnnh2h6foop77l985kgaserblcuibfsc.apps.googleusercontent.com",
          "client_type": 3
        }
      ],
      "api_key": [
        {
          "current_key": "AIzaSyDsPC793-8fOSE4w7NpcT3Siun-yXk7cfw"
        }
      ],
      "services": {
        "analytics_service": {
          "status": 1
        },
        "appinvite_service": {
          "status": 1,
          "other_platform_oauth_client": []
        },
        "ads_service": {
          "status": 2
        }
      }
    }
  ],
  "configuration_version": "1"
}